{
  "update_time": "2026-03-05 05:25:45 KST",
  "hour": 5,
  "realtime": {
    "current_temp": 1.0,
    "max_temp": 3.0,
    "forecast_mean": 6.7,
    "forecast_std": 1.39
  },
  "institutions": [
    {
      "name": "ECMWF (欧洲)",
      "temp": 8.4
    },
    {
      "name": "GFS (美国)",
      "temp": 8.5
    },
    {
      "name": "ICON (德国)",
      "temp": 6.7
    },
    {
      "name": "JMA (日本)",
      "temp": 6.4
    },
    {
      "name": "UKMO (英国)",
      "temp": 5.4
    },
    {
      "name": "CMA (中国)",
      "temp": 4.8
    },
    {
      "name": "Best Match (综合)",
      "temp": "N/A"
    }
  ],
  "chart_data": {
    "hours": [
      "00:00",
      "01:00",
      "02:00",
      "03:00",
      "04:00",
      "05:00",
      "06:00",
      "07:00",
      "08:00",
      "09:00",
      "10:00",
      "11:00",
      "12:00",
      "13:00",
      "14:00",
      "15:00",
      "16:00",
      "17:00",
      "18:00",
      "19:00",
      "20:00",
      "21:00",
      "22:00",
      "23:00"
    ],
    "actual_temp": [
      3.0,
      2.0,
      1.5,
      1.0,
      1.0,
      null,
      null,
      null,
      null,
      null,
      null,
      null,
      null,
      null,
      null,
      null,
      null,
      null,
      null,
      null,
      null,
      null,
      null,
      null
    ],
    "forecasts": {
      "ECMWF (欧洲)": [
        1.9,
        1.1,
        0.3,
        -0.3,
        -0.9,
        -1.3,
        -1.2,
        -0.6,
        0.6,
        2.0,
        4.0,
        6.2,
        7.8,
        8.4,
        8.2,
        7.8,
        7.2,
        6.1,
        5.2,
        4.6,
        4.1,
        3.5,
        3.0,
        2.6
      ],
      "GFS (美国)": [
        3.4,
        3.1,
        3.0,
        2.4,
        2.0,
        2.2,
        2.3,
        1.9,
        2.7,
        4.4,
        6.1,
        7.7,
        8.1,
        8.4,
        8.5,
        8.5,
        8.1,
        7.0,
        6.0,
        4.8,
        3.9,
        2.3,
        1.7,
        1.9
      ],
      "ICON (德国)": [
        4.8,
        4.6,
        4.3,
        4.1,
        3.9,
        3.9,
        3.8,
        3.8,
        3.9,
        4.1,
        4.7,
        5.5,
        6.3,
        6.5,
        6.5,
        6.7,
        6.6,
        6.2,
        5.8,
        5.5,
        4.5,
        4.0,
        3.8,
        3.8
      ],
      "JMA (日本)": [
        1.6,
        0.8,
        0.6,
        0.5,
        0.0,
        -0.1,
        -0.4,
        0.4,
        0.7,
        1.8,
        2.8,
        3.4,
        4.4,
        5.7,
        6.3,
        6.4,
        6.0,
        6.0,
        5.6,
        5.3,
        3.6,
        2.1,
        0.8,
        1.0
      ],
      "UKMO (英国)": [
        4.7,
        4.4,
        4.2,
        4.1,
        4.0,
        3.9,
        4.0,
        4.2,
        4.1,
        3.8,
        3.9,
        4.1,
        4.2,
        4.6,
        4.7,
        5.0,
        5.3,
        5.4,
        5.3,
        5.2,
        5.2,
        3.3,
        3.2,
        3.5
      ],
      "CMA (中国)": [
        3.9,
        3.6,
        3.3,
        3.0,
        2.9,
        2.8,
        2.9,
        3.0,
        3.2,
        3.4,
        3.6,
        3.7,
        3.9,
        4.0,
        4.2,
        4.4,
        4.6,
        4.7,
        4.8,
        4.8,
        4.7,
        4.7,
        4.7,
        4.7
      ]
    }
  },
  "model": {
    "median": 9.91,
    "quantiles": {
      "p05": 7.89,
      "p25": 9.19,
      "p50": 9.91,
      "p75": 10.53,
      "p95": 12.06
    },
    "probabilities": [
      {
        "temp": 10,
        "prob": 38.21
      },
      {
        "temp": 9,
        "prob": 21.41
      },
      {
        "temp": 8,
        "prob": 14.35
      },
      {
        "temp": 11,
        "prob": 13.7
      },
      {
        "temp": 7,
        "prob": 0.0
      }
    ]
  }
}